setup.py
spliopy/__init__.py
spliopy/spliopy.py
spliopy.egg-info/PKG-INFO
spliopy.egg-info/SOURCES.txt
spliopy.egg-info/dependency_links.txt
spliopy.egg-info/pbr.json
spliopy.egg-info/top_level.txt