Metadata-Version: 1.0
Name: spliopy
Version: 1.1.4
Summary: Python wrapper around the API, using Splio API REST 1.0
Home-page: https://github.com/dooplan/spliopy
Author: Pasqual Guerrero
Author-email: pasqual.guerrero@gmail.com
License: MIT
Platform: UNKNOWN
